largentemp_openapi_client/__init__.py
largentemp_openapi_client/client.py
largentemp_openapi_client/exceptions.py
largentemp_openapi_client/models.py
largentemp_openapi_client-0.1.8.dist-info/LICENSE
largentemp_openapi_client-0.1.8.dist-info/METADATA
largentemp_openapi_client-0.1.8.dist-info/WHEEL
largentemp_openapi_client-0.1.8.dist-info/top_level.txt
largentemp_openapi_client-0.1.8.dist-info/RECORD
