Metadata-Version: 2.1
Name: largentemp-openapi-client
Version: 0.1.8
Summary: API-klient för LargenTemps öppna API
Home-page: https://largentemp.pythonanywhere.com/static/templates/apiinfo.html
Author: LargenTemp
Author-email: largentemp@gmail.com
Classifier: Programming Language :: Python :: 3
Classifier: License :: OSI Approved :: MIT License
Classifier: Operating System :: OS Independent
Requires-Python: >=3.7
License-File: LICENSE
Requires-Dist: requests (>=2.27.1)
Requires-Dist: pytz (>=2018.9)
